{
  "project_info": {
    "project_number": "480223056667",
    "project_id": "fotoshare-da11f",
    "storage_bucket": "fotoshare-da11f.appspot.com"
  },
  "client": [
    {
      "client_info": {
        "mobilesdk_app_id": "1:480223056667:android:c08ab4fe79315dab38b9be",
        "android_client_info": {
          "package_name": "com.example.foto_share"
        }
      },
      "oauth_client": [
        {
          "client_id": "480223056667-2totrquivqgalcp1qkf9684o8nscuhj6.apps.googleusercontent.com",
          "client_type": 3
        }
      ],
      "api_key": [
        {
          "current_key": "AIzaSyD-kuvgv1eLg1D1da9hNCwb0N6A_Eo1yZk"
        }
      ],
      "services": {
        "appinvite_service": {
          "other_platform_oauth_client": [
            {
              "client_id": "480223056667-2totrquivqgalcp1qkf9684o8nscuhj6.apps.googleusercontent.com",
              "client_type": 3
            },
            {
              "client_id": "480223056667-1amveeh8afnee9qaodj3425ren9fchfn.apps.googleusercontent.com",
              "client_type": 2,
              "ios_info": {
                "bundle_id": "mx.iteso.fotoShare"
              }
            }
          ]
        }
      }
    }
  ],
  "configuration_version": "1"
}